{
  "last_updated": 1732467832,
  "data": {
    "bikes": [
      {
        "is_reserved": false,
        "vehicle_type_id": "free_streets_scooter",
        "is_disabled": true,
        "current_range_meters": 17797,
        "lon": -3.6685855974674113,
        "bike_id": "free_streets_MADRID001",
        "lat": 40.364267143501614,
        "pricing_plan_id": "free_streets_plan_1"
      },
      {
        "is_reserved": false,
        "vehicle_type_id": "free_streets_motorbike",
        "is_disabled": false,
        "current_range_meters": 84993,
        "lon": -3.601614506885809,
        "bike_id": "free_streets_MADRID002",
        "lat": 40.31070013090151,
        "pricing_plan_id": "free_streets_plan_3"
      },
      {
        "is_reserved": false,
        "vehicle_type_id": "free_streets_motorbike",
        "is_disabled": true,
        "current_range_meters": 153749,
        "lon": -3.6572998900545586,
        "bike_id": "free_streets_MADRID003",
        "lat": 40.48457678193431,
        "pricing_plan_id": "free_streets_plan_1"
      },
      {
        "is_reserved": false,
        "vehicle_type_id": "free_streets_motorbike",
        "is_disabled": true,
        "current_range_meters": 160140,
        "lon": -3.7074613801380036,
        "bike_id": "free_streets_MADRID004",
        "lat": 40.45020907667134,
        "pricing_plan_id": "free_streets_plan_1"
      },
      {
        "is_reserved": true,
        "vehicle_type_id": "free_streets_motorbike",
        "is_disabled": true,
        "current_range_meters": 60492,
        "lon": -3.6144432721507043,
        "bike_id": "free_streets_MADRID005",
        "lat": 40.31185167307557,
        "pricing_plan_id": "free_streets_plan_3"
      },
      {
        "is_reserved": false,
        "vehicle_type_id": "free_streets_scooter",
        "is_disabled": true,
        "current_range_meters": 8407,
        "lon": -3.711289715482539,
        "bike_id": "free_streets_MADRID006",
        "lat": 40.38595408205266,
        "pricing_plan_id": "free_streets_plan_1"
      },
      {
        "is_reserved": false,
        "vehicle_type_id": "free_streets_scooter",
        "is_disabled": false,
        "current_range_meters": 13560,
        "lon": -3.7528542413198216,
        "bike_id": "free_streets_MADRID007",
        "lat": 40.35465104027529,
        "pricing_plan_id": "free_streets_plan_1"
      },
      {
        "is_reserved": false,
        "vehicle_type_id": "free_streets_motorbike",
        "is_disabled": true,
        "current_range_meters": 159460,
        "lon": -3.7565310511045897,
        "bike_id": "free_streets_MADRID008",
        "lat": 40.30724866856132,
        "pricing_plan_id": "free_streets_plan_1"
      },
      {
        "is_reserved": true,
        "vehicle_type_id": "free_streets_scooter",
        "is_disabled": true,
        "current_range_meters": 4262,
        "lon": -3.6187553223938034,
        "bike_id": "free_streets_MADRID009",
        "lat": 40.30307421806105,
        "pricing_plan_id": "free_streets_plan_2"
      },
      {
        "is_reserved": true,
        "vehicle_type_id": "free_streets_motorbike",
        "is_disabled": false,
        "current_range_meters": 130201,
        "lon": -3.6606896046691078,
        "bike_id": "free_streets_MADRID010",
        "lat": 40.435000891654965,
        "pricing_plan_id": "free_streets_plan_3"
      },
      {
        "is_reserved": false,
        "vehicle_type_id": "free_streets_scooter",
        "is_disabled": true,
        "current_range_meters": 8951,
        "lon": -3.7747959541323937,
        "bike_id": "free_streets_MADRID011",
        "lat": 40.33161479505195,
        "pricing_plan_id": "free_streets_plan_3"
      },
      {
        "is_reserved": false,
        "vehicle_type_id": "free_streets_motorbike",
        "is_disabled": true,
        "current_range_meters": 187997,
        "lon": -3.727729308945706,
        "bike_id": "free_streets_MADRID012",
        "lat": 40.32073633250177,
        "pricing_plan_id": "free_streets_plan_2"
      },
      {
        "is_reserved": true,
        "vehicle_type_id": "free_streets_scooter",
        "is_disabled": true,
        "current_range_meters": 15104,
        "lon": -3.7892430820733742,
        "bike_id": "free_streets_MADRID013",
        "lat": 40.39493275115956,
        "pricing_plan_id": "free_streets_plan_2"
      },
      {
        "is_reserved": true,
        "vehicle_type_id": "free_streets_motorbike",
        "is_disabled": false,
        "current_range_meters": 76593,
        "lon": -3.6131087196441074,
        "bike_id": "free_streets_MADRID014",
        "lat": 40.33933407121842,
        "pricing_plan_id": "free_streets_plan_3"
      },
      {
        "is_reserved": true,
        "vehicle_type_id": "free_streets_scooter",
        "is_disabled": true,
        "current_range_meters": 10845,
        "lon": -3.7226061090039897,
        "bike_id": "free_streets_MADRID015",
        "lat": 40.45869163018443,
        "pricing_plan_id": "free_streets_plan_1"
      },
      {
        "is_reserved": false,
        "vehicle_type_id": "free_streets_motorbike",
        "is_disabled": true,
        "current_range_meters": 65993,
        "lon": -3.6785567187171067,
        "bike_id": "free_streets_MADRID016",
        "lat": 40.33304998126997,
        "pricing_plan_id": "free_streets_plan_1"
      },
      {
        "is_reserved": false,
        "vehicle_type_id": "free_streets_scooter",
        "is_disabled": true,
        "current_range_meters": 19979,
        "lon": -3.667493814753437,
        "bike_id": "free_streets_MADRID017",
        "lat": 40.46114131954855,
        "pricing_plan_id": "free_streets_plan_2"
      },
      {
        "is_reserved": false,
        "vehicle_type_id": "free_streets_scooter",
        "is_disabled": true,
        "current_range_meters": 13462,
        "lon": -3.6945834357396174,
        "bike_id": "free_streets_MADRID018",
        "lat": 40.36409592758782,
        "pricing_plan_id": "free_streets_plan_3"
      },
      {
        "is_reserved": true,
        "vehicle_type_id": "free_streets_motorbike",
        "is_disabled": false,
        "current_range_meters": 142425,
        "lon": -3.6133783923855898,
        "bike_id": "free_streets_MADRID019",
        "lat": 40.463403009118466,
        "pricing_plan_id": "free_streets_plan_2"
      },
      {
        "is_reserved": false,
        "vehicle_type_id": "free_streets_scooter",
        "is_disabled": false,
        "current_range_meters": 10599,
        "lon": -3.75162396436696,
        "bike_id": "free_streets_MADRID020",
        "lat": 40.479855340308816,
        "pricing_plan_id": "free_streets_plan_1"
      },
      {
        "is_reserved": true,
        "vehicle_type_id": "free_streets_scooter",
        "is_disabled": false,
        "current_range_meters": 13706,
        "lon": -3.642139097066437,
        "bike_id": "free_streets_MADRID021",
        "lat": 40.47658053500561,
        "pricing_plan_id": "free_streets_plan_3"
      },
      {
        "is_reserved": false,
        "vehicle_type_id": "free_streets_motorbike",
        "is_disabled": false,
        "current_range_meters": 138769,
        "lon": -3.635128321572104,
        "bike_id": "free_streets_MADRID022",
        "lat": 40.308028202253205,
        "pricing_plan_id": "free_streets_plan_3"
      },
      {
        "is_reserved": true,
        "vehicle_type_id": "free_streets_motorbike",
        "is_disabled": true,
        "current_range_meters": 93677,
        "lon": -3.6323709232451318,
        "bike_id": "free_streets_MADRID023",
        "lat": 40.469510609955044,
        "pricing_plan_id": "free_streets_plan_1"
      },
      {
        "is_reserved": false,
        "vehicle_type_id": "free_streets_motorbike",
        "is_disabled": false,
        "current_range_meters": 66999,
        "lon": -3.7453912068651842,
        "bike_id": "free_streets_MADRID024",
        "lat": 40.34054856601927,
        "pricing_plan_id": "free_streets_plan_3"
      },
      {
        "is_reserved": true,
        "vehicle_type_id": "free_streets_scooter",
        "is_disabled": true,
        "current_range_meters": 12693,
        "lon": -3.764727330961727,
        "bike_id": "free_streets_MADRID025",
        "lat": 40.40577384259156,
        "pricing_plan_id": "free_streets_plan_3"
      },
      {
        "is_reserved": false,
        "vehicle_type_id": "free_streets_scooter",
        "is_disabled": false,
        "current_range_meters": 2952,
        "lon": -3.7634233662628076,
        "bike_id": "free_streets_MADRID026",
        "lat": 40.363874089990404,
        "pricing_plan_id": "free_streets_plan_2"
      },
      {
        "is_reserved": false,
        "vehicle_type_id": "free_streets_scooter",
        "is_disabled": true,
        "current_range_meters": 9139,
        "lon": -3.708404429610023,
        "bike_id": "free_streets_MADRID027",
        "lat": 40.32710369878303,
        "pricing_plan_id": "free_streets_plan_1"
      },
      {
        "is_reserved": false,
        "vehicle_type_id": "free_streets_motorbike",
        "is_disabled": true,
        "current_range_meters": 112226,
        "lon": -3.6232914017963824,
        "bike_id": "free_streets_MADRID028",
        "lat": 40.39204521176631,
        "pricing_plan_id": "free_streets_plan_2"
      },
      {
        "is_reserved": false,
        "vehicle_type_id": "free_streets_scooter",
        "is_disabled": true,
        "current_range_meters": 13701,
        "lon": -3.747166452262714,
        "bike_id": "free_streets_MADRID029",
        "lat": 40.333934020674654,
        "pricing_plan_id": "free_streets_plan_3"
      },
      {
        "is_reserved": false,
        "vehicle_type_id": "free_streets_motorbike",
        "is_disabled": false,
        "current_range_meters": 145985,
        "lon": -3.7594547831883127,
        "bike_id": "free_streets_MADRID030",
        "lat": 40.45699723507394,
        "pricing_plan_id": "free_streets_plan_3"
      },
      {
        "is_reserved": false,
        "vehicle_type_id": "free_streets_scooter",
        "is_disabled": false,
        "current_range_meters": 15477,
        "lon": -3.6729949529215706,
        "bike_id": "free_streets_MADRID031",
        "lat": 40.41184126557039,
        "pricing_plan_id": "free_streets_plan_2"
      },
      {
        "is_reserved": true,
        "vehicle_type_id": "free_streets_motorbike",
        "is_disabled": true,
        "current_range_meters": 118486,
        "lon": -3.665761243450786,
        "bike_id": "free_streets_MADRID032",
        "lat": 40.38039777731502,
        "pricing_plan_id": "free_streets_plan_2"
      },
      {
        "is_reserved": true,
        "vehicle_type_id": "free_streets_scooter",
        "is_disabled": true,
        "current_range_meters": 4283,
        "lon": -3.7531204255591493,
        "bike_id": "free_streets_MADRID033",
        "lat": 40.324590218665804,
        "pricing_plan_id": "free_streets_plan_3"
      },
      {
        "is_reserved": false,
        "vehicle_type_id": "free_streets_motorbike",
        "is_disabled": false,
        "current_range_meters": 181442,
        "lon": -3.7319678118954704,
        "bike_id": "free_streets_MADRID034",
        "lat": 40.4645941239172,
        "pricing_plan_id": "free_streets_plan_2"
      },
      {
        "is_reserved": true,
        "vehicle_type_id": "free_streets_motorbike",
        "is_disabled": false,
        "current_range_meters": 175527,
        "lon": -3.6705862954625905,
        "bike_id": "free_streets_MADRID035",
        "lat": 40.4105094308902,
        "pricing_plan_id": "free_streets_plan_3"
      },
      {
        "is_reserved": false,
        "vehicle_type_id": "free_streets_motorbike",
        "is_disabled": false,
        "current_range_meters": 38902,
        "lon": -3.70197490339259,
        "bike_id": "free_streets_MADRID036",
        "lat": 40.345425170217844,
        "pricing_plan_id": "free_streets_plan_1"
      },
      {
        "is_reserved": false,
        "vehicle_type_id": "free_streets_motorbike",
        "is_disabled": false,
        "current_range_meters": 93462,
        "lon": -3.6521877008966572,
        "bike_id": "free_streets_MADRID037",
        "lat": 40.49656537174545,
        "pricing_plan_id": "free_streets_plan_2"
      },
      {
        "is_reserved": true,
        "vehicle_type_id": "free_streets_motorbike",
        "is_disabled": false,
        "current_range_meters": 36916,
        "lon": -3.651251892953711,
        "bike_id": "free_streets_MADRID038",
        "lat": 40.39717702245428,
        "pricing_plan_id": "free_streets_plan_1"
      },
      {
        "is_reserved": false,
        "vehicle_type_id": "free_streets_scooter",
        "is_disabled": true,
        "current_range_meters": 7034,
        "lon": -3.7533294583103127,
        "bike_id": "free_streets_MADRID039",
        "lat": 40.44154945862381,
        "pricing_plan_id": "free_streets_plan_1"
      },
      {
        "is_reserved": true,
        "vehicle_type_id": "free_streets_motorbike",
        "is_disabled": false,
        "current_range_meters": 32207,
        "lon": -3.7673370567270585,
        "bike_id": "free_streets_MADRID040",
        "lat": 40.30058805045533,
        "pricing_plan_id": "free_streets_plan_1"
      },
      {
        "is_reserved": true,
        "vehicle_type_id": "free_streets_scooter",
        "is_disabled": false,
        "current_range_meters": 10736,
        "lon": -3.6286259937170406,
        "bike_id": "free_streets_MADRID041",
        "lat": 40.4837590228912,
        "pricing_plan_id": "free_streets_plan_2"
      },
      {
        "is_reserved": false,
        "vehicle_type_id": "free_streets_motorbike",
        "is_disabled": true,
        "current_range_meters": 207832,
        "lon": -3.648957673966144,
        "bike_id": "free_streets_MADRID042",
        "lat": 40.38022168240292,
        "pricing_plan_id": "free_streets_plan_3"
      },
      {
        "is_reserved": false,
        "vehicle_type_id": "free_streets_motorbike",
        "is_disabled": true,
        "current_range_meters": 151495,
        "lon": -3.7782853979352966,
        "bike_id": "free_streets_MADRID043",
        "lat": 40.42499622163519,
        "pricing_plan_id": "free_streets_plan_1"
      },
      {
        "is_reserved": false,
        "vehicle_type_id": "free_streets_scooter",
        "is_disabled": true,
        "current_range_meters": 15142,
        "lon": -3.7586912185353163,
        "bike_id": "free_streets_MADRID044",
        "lat": 40.330034424018514,
        "pricing_plan_id": "free_streets_plan_3"
      },
      {
        "is_reserved": false,
        "vehicle_type_id": "free_streets_scooter",
        "is_disabled": true,
        "current_range_meters": 9469,
        "lon": -3.6912455220478284,
        "bike_id": "free_streets_MADRID045",
        "lat": 40.425560646979804,
        "pricing_plan_id": "free_streets_plan_2"
      },
      {
        "is_reserved": false,
        "vehicle_type_id": "free_streets_motorbike",
        "is_disabled": true,
        "current_range_meters": 74833,
        "lon": -3.6959273349809325,
        "bike_id": "free_streets_MADRID046",
        "lat": 40.32985946021639,
        "pricing_plan_id": "free_streets_plan_2"
      },
      {
        "is_reserved": false,
        "vehicle_type_id": "free_streets_motorbike",
        "is_disabled": true,
        "current_range_meters": 205173,
        "lon": -3.7853210871559644,
        "bike_id": "free_streets_MADRID047",
        "lat": 40.36341126262875,
        "pricing_plan_id": "free_streets_plan_3"
      },
      {
        "is_reserved": false,
        "vehicle_type_id": "free_streets_motorbike",
        "is_disabled": true,
        "current_range_meters": 59535,
        "lon": -3.700760576152183,
        "bike_id": "free_streets_MADRID048",
        "lat": 40.47898291145698,
        "pricing_plan_id": "free_streets_plan_3"
      },
      {
        "is_reserved": false,
        "vehicle_type_id": "free_streets_scooter",
        "is_disabled": false,
        "current_range_meters": 7618,
        "lon": -3.6551763043594994,
        "bike_id": "free_streets_MADRID049",
        "lat": 40.38865482728735,
        "pricing_plan_id": "free_streets_plan_1"
      },
      {
        "is_reserved": false,
        "vehicle_type_id": "free_streets_scooter",
        "is_disabled": false,
        "current_range_meters": 3584,
        "lon": -3.721365816100341,
        "bike_id": "free_streets_MADRID050",
        "lat": 40.435723219799186,
        "pricing_plan_id": "free_streets_plan_2"
      },
      {
        "is_reserved": false,
        "vehicle_type_id": "free_streets_scooter",
        "is_disabled": false,
        "current_range_meters": 4585,
        "lon": -3.674818800745427,
        "bike_id": "free_streets_MADRID051",
        "lat": 40.499094001312464,
        "pricing_plan_id": "free_streets_plan_3"
      },
      {
        "is_reserved": true,
        "vehicle_type_id": "free_streets_motorbike",
        "is_disabled": false,
        "current_range_meters": 98193,
        "lon": -3.7029595411623815,
        "bike_id": "free_streets_MADRID052",
        "lat": 40.30994689417492,
        "pricing_plan_id": "free_streets_plan_2"
      },
      {
        "is_reserved": true,
        "vehicle_type_id": "free_streets_motorbike",
        "is_disabled": true,
        "current_range_meters": 136045,
        "lon": -3.718704864166811,
        "bike_id": "free_streets_MADRID053",
        "lat": 40.3504910363614,
        "pricing_plan_id": "free_streets_plan_3"
      },
      {
        "is_reserved": false,
        "vehicle_type_id": "free_streets_scooter",
        "is_disabled": true,
        "current_range_meters": 13478,
        "lon": -3.6614264137034973,
        "bike_id": "free_streets_MADRID054",
        "lat": 40.30063256107796,
        "pricing_plan_id": "free_streets_plan_1"
      },
      {
        "is_reserved": true,
        "vehicle_type_id": "free_streets_motorbike",
        "is_disabled": true,
        "current_range_meters": 133273,
        "lon": -3.6269924047586772,
        "bike_id": "free_streets_MADRID055",
        "lat": 40.32642987063888,
        "pricing_plan_id": "free_streets_plan_1"
      },
      {
        "is_reserved": false,
        "vehicle_type_id": "free_streets_motorbike",
        "is_disabled": true,
        "current_range_meters": 193156,
        "lon": -3.6431691513080287,
        "bike_id": "free_streets_MADRID056",
        "lat": 40.31889458622606,
        "pricing_plan_id": "free_streets_plan_3"
      },
      {
        "is_reserved": true,
        "vehicle_type_id": "free_streets_scooter",
        "is_disabled": false,
        "current_range_meters": 4086,
        "lon": -3.7703254250273432,
        "bike_id": "free_streets_MADRID057",
        "lat": 40.39190955105407,
        "pricing_plan_id": "free_streets_plan_3"
      },
      {
        "is_reserved": false,
        "vehicle_type_id": "free_streets_scooter",
        "is_disabled": false,
        "current_range_meters": 5971,
        "lon": -3.7761410134271305,
        "bike_id": "free_streets_MADRID058",
        "lat": 40.33545278421707,
        "pricing_plan_id": "free_streets_plan_2"
      },
      {
        "is_reserved": false,
        "vehicle_type_id": "free_streets_motorbike",
        "is_disabled": true,
        "current_range_meters": 79300,
        "lon": -3.7573441988085983,
        "bike_id": "free_streets_MADRID059",
        "lat": 40.34312957926828,
        "pricing_plan_id": "free_streets_plan_1"
      },
      {
        "is_reserved": true,
        "vehicle_type_id": "free_streets_motorbike",
        "is_disabled": true,
        "current_range_meters": 115331,
        "lon": -3.7415058494788775,
        "bike_id": "free_streets_MADRID060",
        "lat": 40.46107751634735,
        "pricing_plan_id": "free_streets_plan_3"
      },
      {
        "is_reserved": true,
        "vehicle_type_id": "free_streets_motorbike",
        "is_disabled": false,
        "current_range_meters": 111321,
        "lon": -3.685490777131655,
        "bike_id": "free_streets_MADRID061",
        "lat": 40.31559907255219,
        "pricing_plan_id": "free_streets_plan_1"
      },
      {
        "is_reserved": true,
        "vehicle_type_id": "free_streets_scooter",
        "is_disabled": false,
        "current_range_meters": 13805,
        "lon": -3.788678831017519,
        "bike_id": "free_streets_MADRID062",
        "lat": 40.45353503678929,
        "pricing_plan_id": "free_streets_plan_1"
      },
      {
        "is_reserved": false,
        "vehicle_type_id": "free_streets_motorbike",
        "is_disabled": true,
        "current_range_meters": 18329,
        "lon": -3.6307185331380056,
        "bike_id": "free_streets_MADRID063",
        "lat": 40.47990095991547,
        "pricing_plan_id": "free_streets_plan_3"
      },
      {
        "is_reserved": false,
        "vehicle_type_id": "free_streets_scooter",
        "is_disabled": false,
        "current_range_meters": 6902,
        "lon": -3.719055309887624,
        "bike_id": "free_streets_MADRID064",
        "lat": 40.35035665168514,
        "pricing_plan_id": "free_streets_plan_1"
      },
      {
        "is_reserved": true,
        "vehicle_type_id": "free_streets_motorbike",
        "is_disabled": false,
        "current_range_meters": 167094,
        "lon": -3.6340829584563212,
        "bike_id": "free_streets_MADRID065",
        "lat": 40.495593955753606,
        "pricing_plan_id": "free_streets_plan_1"
      },
      {
        "is_reserved": false,
        "vehicle_type_id": "free_streets_motorbike",
        "is_disabled": true,
        "current_range_meters": 191277,
        "lon": -3.652628724838733,
        "bike_id": "free_streets_MADRID066",
        "lat": 40.37861920723252,
        "pricing_plan_id": "free_streets_plan_2"
      },
      {
        "is_reserved": false,
        "vehicle_type_id": "free_streets_scooter",
        "is_disabled": false,
        "current_range_meters": 15009,
        "lon": -3.6515067157980527,
        "bike_id": "free_streets_MADRID067",
        "lat": 40.34246789998208,
        "pricing_plan_id": "free_streets_plan_2"
      },
      {
        "is_reserved": true,
        "vehicle_type_id": "free_streets_scooter",
        "is_disabled": true,
        "current_range_meters": 13576,
        "lon": -3.7198886612491164,
        "bike_id": "free_streets_MADRID068",
        "lat": 40.45845086548484,
        "pricing_plan_id": "free_streets_plan_2"
      },
      {
        "is_reserved": false,
        "vehicle_type_id": "free_streets_motorbike",
        "is_disabled": false,
        "current_range_meters": 61839,
        "lon": -3.76503313707508,
        "bike_id": "free_streets_MADRID069",
        "lat": 40.3914071126921,
        "pricing_plan_id": "free_streets_plan_2"
      },
      {
        "is_reserved": false,
        "vehicle_type_id": "free_streets_scooter",
        "is_disabled": false,
        "current_range_meters": 10971,
        "lon": -3.798205105023112,
        "bike_id": "free_streets_MADRID070",
        "lat": 40.3895575945128,
        "pricing_plan_id": "free_streets_plan_3"
      },
      {
        "is_reserved": true,
        "vehicle_type_id": "free_streets_motorbike",
        "is_disabled": true,
        "current_range_meters": 104492,
        "lon": -3.698698147356983,
        "bike_id": "free_streets_MADRID071",
        "lat": 40.49863109452509,
        "pricing_plan_id": "free_streets_plan_1"
      },
      {
        "is_reserved": false,
        "vehicle_type_id": "free_streets_motorbike",
        "is_disabled": true,
        "current_range_meters": 181519,
        "lon": -3.6147016394002045,
        "bike_id": "free_streets_MADRID072",
        "lat": 40.357290294444475,
        "pricing_plan_id": "free_streets_plan_2"
      },
      {
        "is_reserved": false,
        "vehicle_type_id": "free_streets_scooter",
        "is_disabled": false,
        "current_range_meters": 12772,
        "lon": -3.6823588250103385,
        "bike_id": "free_streets_MADRID073",
        "lat": 40.35227168650712,
        "pricing_plan_id": "free_streets_plan_3"
      },
      {
        "is_reserved": false,
        "vehicle_type_id": "free_streets_motorbike",
        "is_disabled": true,
        "current_range_meters": 36200,
        "lon": -3.7381870471688323,
        "bike_id": "free_streets_MADRID074",
        "lat": 40.43192282373862,
        "pricing_plan_id": "free_streets_plan_2"
      },
      {
        "is_reserved": true,
        "vehicle_type_id": "free_streets_motorbike",
        "is_disabled": true,
        "current_range_meters": 119413,
        "lon": -3.6173980606109946,
        "bike_id": "free_streets_MADRID075",
        "lat": 40.440197395110914,
        "pricing_plan_id": "free_streets_plan_1"
      },
      {
        "is_reserved": true,
        "vehicle_type_id": "free_streets_scooter",
        "is_disabled": true,
        "current_range_meters": 19897,
        "lon": -3.715765697427899,
        "bike_id": "free_streets_MADRID076",
        "lat": 40.3898669027611,
        "pricing_plan_id": "free_streets_plan_1"
      },
      {
        "is_reserved": true,
        "vehicle_type_id": "free_streets_scooter",
        "is_disabled": false,
        "current_range_meters": 16294,
        "lon": -3.717583947627346,
        "bike_id": "free_streets_MADRID077",
        "lat": 40.369088112486715,
        "pricing_plan_id": "free_streets_plan_1"
      },
      {
        "is_reserved": false,
        "vehicle_type_id": "free_streets_motorbike",
        "is_disabled": false,
        "current_range_meters": 108515,
        "lon": -3.7046001138463236,
        "bike_id": "free_streets_MADRID078",
        "lat": 40.37834950691125,
        "pricing_plan_id": "free_streets_plan_1"
      },
      {
        "is_reserved": true,
        "vehicle_type_id": "free_streets_motorbike",
        "is_disabled": true,
        "current_range_meters": 201746,
        "lon": -3.6457591633879765,
        "bike_id": "free_streets_MADRID079",
        "lat": 40.417158985155645,
        "pricing_plan_id": "free_streets_plan_2"
      },
      {
        "is_reserved": true,
        "vehicle_type_id": "free_streets_scooter",
        "is_disabled": false,
        "current_range_meters": 4643,
        "lon": -3.6895782455889634,
        "bike_id": "free_streets_MADRID080",
        "lat": 40.40954974710986,
        "pricing_plan_id": "free_streets_plan_2"
      },
      {
        "is_reserved": false,
        "vehicle_type_id": "free_streets_scooter",
        "is_disabled": true,
        "current_range_meters": 18094,
        "lon": -3.6493683623969027,
        "bike_id": "free_streets_MADRID081",
        "lat": 40.38392614664008,
        "pricing_plan_id": "free_streets_plan_1"
      },
      {
        "is_reserved": true,
        "vehicle_type_id": "free_streets_scooter",
        "is_disabled": true,
        "current_range_meters": 11045,
        "lon": -3.6476020493279955,
        "bike_id": "free_streets_MADRID082",
        "lat": 40.404802422593605,
        "pricing_plan_id": "free_streets_plan_2"
      },
      {
        "is_reserved": true,
        "vehicle_type_id": "free_streets_motorbike",
        "is_disabled": true,
        "current_range_meters": 163683,
        "lon": -3.62749582469707,
        "bike_id": "free_streets_MADRID083",
        "lat": 40.47967581620479,
        "pricing_plan_id": "free_streets_plan_3"
      },
      {
        "is_reserved": false,
        "vehicle_type_id": "free_streets_scooter",
        "is_disabled": false,
        "current_range_meters": 14045,
        "lon": -3.6390443207754157,
        "bike_id": "free_streets_MADRID084",
        "lat": 40.347312748867914,
        "pricing_plan_id": "free_streets_plan_2"
      },
      {
        "is_reserved": false,
        "vehicle_type_id": "free_streets_scooter",
        "is_disabled": true,
        "current_range_meters": 20169,
        "lon": -3.7563777340613513,
        "bike_id": "free_streets_MADRID085",
        "lat": 40.37232168043098,
        "pricing_plan_id": "free_streets_plan_3"
      },
      {
        "is_reserved": true,
        "vehicle_type_id": "free_streets_scooter",
        "is_disabled": false,
        "current_range_meters": 19407,
        "lon": -3.653072311410995,
        "bike_id": "free_streets_MADRID086",
        "lat": 40.447965675982346,
        "pricing_plan_id": "free_streets_plan_1"
      },
      {
        "is_reserved": false,
        "vehicle_type_id": "free_streets_motorbike",
        "is_disabled": true,
        "current_range_meters": 118677,
        "lon": -3.7116317239979786,
        "bike_id": "free_streets_MADRID087",
        "lat": 40.350524828966414,
        "pricing_plan_id": "free_streets_plan_1"
      },
      {
        "is_reserved": false,
        "vehicle_type_id": "free_streets_motorbike",
        "is_disabled": true,
        "current_range_meters": 73032,
        "lon": -3.683988577517475,
        "bike_id": "free_streets_MADRID088",
        "lat": 40.41887158793141,
        "pricing_plan_id": "free_streets_plan_3"
      },
      {
        "is_reserved": false,
        "vehicle_type_id": "free_streets_scooter",
        "is_disabled": true,
        "current_range_meters": 8282,
        "lon": -3.620026951008864,
        "bike_id": "free_streets_MADRID089",
        "lat": 40.30826822353617,
        "pricing_plan_id": "free_streets_plan_3"
      },
      {
        "is_reserved": false,
        "vehicle_type_id": "free_streets_scooter",
        "is_disabled": true,
        "current_range_meters": 8611,
        "lon": -3.6537427030731684,
        "bike_id": "free_streets_MADRID090",
        "lat": 40.33933461461502,
        "pricing_plan_id": "free_streets_plan_1"
      },
      {
        "is_reserved": false,
        "vehicle_type_id": "free_streets_motorbike",
        "is_disabled": true,
        "current_range_meters": 146652,
        "lon": -3.796117723355338,
        "bike_id": "free_streets_MADRID091",
        "lat": 40.393172996815714,
        "pricing_plan_id": "free_streets_plan_3"
      },
      {
        "is_reserved": false,
        "vehicle_type_id": "free_streets_motorbike",
        "is_disabled": false,
        "current_range_meters": 68073,
        "lon": -3.6494321865900443,
        "bike_id": "free_streets_MADRID092",
        "lat": 40.403133390132496,
        "pricing_plan_id": "free_streets_plan_2"
      },
      {
        "is_reserved": true,
        "vehicle_type_id": "free_streets_scooter",
        "is_disabled": true,
        "current_range_meters": 20387,
        "lon": -3.747660154939965,
        "bike_id": "free_streets_MADRID093",
        "lat": 40.49499107134312,
        "pricing_plan_id": "free_streets_plan_3"
      },
      {
        "is_reserved": false,
        "vehicle_type_id": "free_streets_scooter",
        "is_disabled": false,
        "current_range_meters": 16999,
        "lon": -3.6334279235769698,
        "bike_id": "free_streets_MADRID094",
        "lat": 40.48471600279629,
        "pricing_plan_id": "free_streets_plan_3"
      },
      {
        "is_reserved": true,
        "vehicle_type_id": "free_streets_motorbike",
        "is_disabled": false,
        "current_range_meters": 138187,
        "lon": -3.6505631774771623,
        "bike_id": "free_streets_MADRID095",
        "lat": 40.42307812456864,
        "pricing_plan_id": "free_streets_plan_3"
      },
      {
        "is_reserved": true,
        "vehicle_type_id": "free_streets_motorbike",
        "is_disabled": false,
        "current_range_meters": 39039,
        "lon": -3.786898075464083,
        "bike_id": "free_streets_MADRID096",
        "lat": 40.45904158375759,
        "pricing_plan_id": "free_streets_plan_1"
      },
      {
        "is_reserved": true,
        "vehicle_type_id": "free_streets_motorbike",
        "is_disabled": true,
        "current_range_meters": 100313,
        "lon": -3.763792720346897,
        "bike_id": "free_streets_MADRID097",
        "lat": 40.38869076475245,
        "pricing_plan_id": "free_streets_plan_2"
      },
      {
        "is_reserved": false,
        "vehicle_type_id": "free_streets_scooter",
        "is_disabled": false,
        "current_range_meters": 17757,
        "lon": -3.7024814973671076,
        "bike_id": "free_streets_MADRID098",
        "lat": 40.32467946182863,
        "pricing_plan_id": "free_streets_plan_1"
      },
      {
        "is_reserved": false,
        "vehicle_type_id": "free_streets_motorbike",
        "is_disabled": false,
        "current_range_meters": 204816,
        "lon": -3.6225429981823094,
        "bike_id": "free_streets_MADRID099",
        "lat": 40.444917545215844,
        "pricing_plan_id": "free_streets_plan_3"
      },
      {
        "is_reserved": true,
        "vehicle_type_id": "free_streets_scooter",
        "is_disabled": true,
        "current_range_meters": 14807,
        "lon": -3.625927812086675,
        "bike_id": "free_streets_MADRID100",
        "lat": 40.31488834191123,
        "pricing_plan_id": "free_streets_plan_3"
      },
      {
        "is_reserved": false,
        "vehicle_type_id": "free_streets_scooter",
        "is_disabled": true,
        "current_range_meters": 8771,
        "lon": -3.7389146432346565,
        "bike_id": "free_streets_MADRID101",
        "lat": 40.40295962600833,
        "pricing_plan_id": "free_streets_plan_1"
      },
      {
        "is_reserved": false,
        "vehicle_type_id": "free_streets_motorbike",
        "is_disabled": false,
        "current_range_meters": 80815,
        "lon": -3.6868505603383763,
        "bike_id": "free_streets_MADRID102",
        "lat": 40.41365531551299,
        "pricing_plan_id": "free_streets_plan_3"
      },
      {
        "is_reserved": true,
        "vehicle_type_id": "free_streets_scooter",
        "is_disabled": false,
        "current_range_meters": 6088,
        "lon": -3.7556421016260364,
        "bike_id": "free_streets_MADRID103",
        "lat": 40.37700982874781,
        "pricing_plan_id": "free_streets_plan_2"
      },
      {
        "is_reserved": true,
        "vehicle_type_id": "free_streets_scooter",
        "is_disabled": false,
        "current_range_meters": 5440,
        "lon": -3.761278312348603,
        "bike_id": "free_streets_MADRID104",
        "lat": 40.39313190334906,
        "pricing_plan_id": "free_streets_plan_3"
      },
      {
        "is_reserved": false,
        "vehicle_type_id": "free_streets_scooter",
        "is_disabled": true,
        "current_range_meters": 14390,
        "lon": -3.6855959218400516,
        "bike_id": "free_streets_MADRID105",
        "lat": 40.407143455566434,
        "pricing_plan_id": "free_streets_plan_1"
      },
      {
        "is_reserved": true,
        "vehicle_type_id": "free_streets_scooter",
        "is_disabled": true,
        "current_range_meters": 14663,
        "lon": -3.689242870048101,
        "bike_id": "free_streets_MADRID106",
        "lat": 40.47506770094887,
        "pricing_plan_id": "free_streets_plan_1"
      },
      {
        "is_reserved": true,
        "vehicle_type_id": "free_streets_scooter",
        "is_disabled": false,
        "current_range_meters": 6996,
        "lon": -3.736320173370049,
        "bike_id": "free_streets_MADRID107",
        "lat": 40.46517458305993,
        "pricing_plan_id": "free_streets_plan_2"
      },
      {
        "is_reserved": true,
        "vehicle_type_id": "free_streets_scooter",
        "is_disabled": true,
        "current_range_meters": 15058,
        "lon": -3.7155643919158323,
        "bike_id": "free_streets_MADRID108",
        "lat": 40.320985330580875,
        "pricing_plan_id": "free_streets_plan_3"
      },
      {
        "is_reserved": false,
        "vehicle_type_id": "free_streets_motorbike",
        "is_disabled": true,
        "current_range_meters": 196055,
        "lon": -3.7656716376276624,
        "bike_id": "free_streets_MADRID109",
        "lat": 40.42429807142745,
        "pricing_plan_id": "free_streets_plan_2"
      },
      {
        "is_reserved": true,
        "vehicle_type_id": "free_streets_scooter",
        "is_disabled": true,
        "current_range_meters": 18308,
        "lon": -3.69953746050796,
        "bike_id": "free_streets_MADRID110",
        "lat": 40.499978831491305,
        "pricing_plan_id": "free_streets_plan_1"
      },
      {
        "is_reserved": false,
        "vehicle_type_id": "free_streets_motorbike",
        "is_disabled": true,
        "current_range_meters": 103182,
        "lon": -3.6484403459383716,
        "bike_id": "free_streets_MADRID111",
        "lat": 40.48873992306285,
        "pricing_plan_id": "free_streets_plan_1"
      },
      {
        "is_reserved": false,
        "vehicle_type_id": "free_streets_motorbike",
        "is_disabled": false,
        "current_range_meters": 178049,
        "lon": -3.626447878986008,
        "bike_id": "free_streets_MADRID112",
        "lat": 40.33445052702415,
        "pricing_plan_id": "free_streets_plan_2"
      },
      {
        "is_reserved": false,
        "vehicle_type_id": "free_streets_motorbike",
        "is_disabled": false,
        "current_range_meters": 118125,
        "lon": -3.6074229874775714,
        "bike_id": "free_streets_MADRID113",
        "lat": 40.498459616448955,
        "pricing_plan_id": "free_streets_plan_1"
      },
      {
        "is_reserved": true,
        "vehicle_type_id": "free_streets_scooter",
        "is_disabled": false,
        "current_range_meters": 12905,
        "lon": -3.737627354824718,
        "bike_id": "free_streets_MADRID114",
        "lat": 40.370676477106066,
        "pricing_plan_id": "free_streets_plan_1"
      },
      {
        "is_reserved": true,
        "vehicle_type_id": "free_streets_scooter",
        "is_disabled": true,
        "current_range_meters": 6332,
        "lon": -3.7033977091133905,
        "bike_id": "free_streets_MADRID115",
        "lat": 40.44655207805227,
        "pricing_plan_id": "free_streets_plan_3"
      },
      {
        "is_reserved": false,
        "vehicle_type_id": "free_streets_scooter",
        "is_disabled": false,
        "current_range_meters": 19975,
        "lon": -3.7502434416247925,
        "bike_id": "free_streets_MADRID116",
        "lat": 40.38859611550622,
        "pricing_plan_id": "free_streets_plan_3"
      },
      {
        "is_reserved": false,
        "vehicle_type_id": "free_streets_motorbike",
        "is_disabled": true,
        "current_range_meters": 35186,
        "lon": -3.6370896049540575,
        "bike_id": "free_streets_MADRID117",
        "lat": 40.39471674206689,
        "pricing_plan_id": "free_streets_plan_1"
      },
      {
        "is_reserved": true,
        "vehicle_type_id": "free_streets_scooter",
        "is_disabled": false,
        "current_range_meters": 5991,
        "lon": -3.6747145827643974,
        "bike_id": "free_streets_MADRID118",
        "lat": 40.41256456374856,
        "pricing_plan_id": "free_streets_plan_1"
      },
      {
        "is_reserved": false,
        "vehicle_type_id": "free_streets_motorbike",
        "is_disabled": false,
        "current_range_meters": 76983,
        "lon": -3.681574573569104,
        "bike_id": "free_streets_MADRID119",
        "lat": 40.3839868131843,
        "pricing_plan_id": "free_streets_plan_2"
      },
      {
        "is_reserved": true,
        "vehicle_type_id": "free_streets_scooter",
        "is_disabled": false,
        "current_range_meters": 18112,
        "lon": -3.6677896238919456,
        "bike_id": "free_streets_MADRID120",
        "lat": 40.33288373200652,
        "pricing_plan_id": "free_streets_plan_3"
      },
      {
        "is_reserved": false,
        "vehicle_type_id": "free_streets_motorbike",
        "is_disabled": true,
        "current_range_meters": 189438,
        "lon": -3.765803121431087,
        "bike_id": "free_streets_MADRID121",
        "lat": 40.38017423372917,
        "pricing_plan_id": "free_streets_plan_1"
      },
      {
        "is_reserved": false,
        "vehicle_type_id": "free_streets_scooter",
        "is_disabled": false,
        "current_range_meters": 8986,
        "lon": -3.7023954701449577,
        "bike_id": "free_streets_MADRID122",
        "lat": 40.45234213614129,
        "pricing_plan_id": "free_streets_plan_1"
      },
      {
        "is_reserved": true,
        "vehicle_type_id": "free_streets_scooter",
        "is_disabled": false,
        "current_range_meters": 17200,
        "lon": -3.7655811683180564,
        "bike_id": "free_streets_MADRID123",
        "lat": 40.414553569329826,
        "pricing_plan_id": "free_streets_plan_3"
      },
      {
        "is_reserved": false,
        "vehicle_type_id": "free_streets_motorbike",
        "is_disabled": false,
        "current_range_meters": 28501,
        "lon": -3.6507684269398024,
        "bike_id": "free_streets_MADRID124",
        "lat": 40.456023646670786,
        "pricing_plan_id": "free_streets_plan_3"
      },
      {
        "is_reserved": true,
        "vehicle_type_id": "free_streets_motorbike",
        "is_disabled": false,
        "current_range_meters": 36503,
        "lon": -3.744051714635087,
        "bike_id": "free_streets_MADRID125",
        "lat": 40.42358975967841,
        "pricing_plan_id": "free_streets_plan_3"
      },
      {
        "is_reserved": true,
        "vehicle_type_id": "free_streets_motorbike",
        "is_disabled": false,
        "current_range_meters": 69681,
        "lon": -3.690763762493027,
        "bike_id": "free_streets_MADRID126",
        "lat": 40.32313064471789,
        "pricing_plan_id": "free_streets_plan_2"
      },
      {
        "is_reserved": false,
        "vehicle_type_id": "free_streets_motorbike",
        "is_disabled": true,
        "current_range_meters": 83527,
        "lon": -3.762530710227405,
        "bike_id": "free_streets_MADRID127",
        "lat": 40.31129026228493,
        "pricing_plan_id": "free_streets_plan_1"
      },
      {
        "is_reserved": false,
        "vehicle_type_id": "free_streets_motorbike",
        "is_disabled": false,
        "current_range_meters": 142523,
        "lon": -3.6838723423815507,
        "bike_id": "free_streets_MADRID128",
        "lat": 40.42460170927276,
        "pricing_plan_id": "free_streets_plan_3"
      },
      {
        "is_reserved": false,
        "vehicle_type_id": "free_streets_motorbike",
        "is_disabled": true,
        "current_range_meters": 32801,
        "lon": -3.6758748823346514,
        "bike_id": "free_streets_MADRID129",
        "lat": 40.363630288743686,
        "pricing_plan_id": "free_streets_plan_3"
      },
      {
        "is_reserved": true,
        "vehicle_type_id": "free_streets_scooter",
        "is_disabled": true,
        "current_range_meters": 14982,
        "lon": -3.619681159968783,
        "bike_id": "free_streets_MADRID130",
        "lat": 40.48391002820051,
        "pricing_plan_id": "free_streets_plan_1"
      },
      {
        "is_reserved": true,
        "vehicle_type_id": "free_streets_motorbike",
        "is_disabled": false,
        "current_range_meters": 168656,
        "lon": -3.7434377730232447,
        "bike_id": "free_streets_MADRID131",
        "lat": 40.33146546577528,
        "pricing_plan_id": "free_streets_plan_2"
      },
      {
        "is_reserved": true,
        "vehicle_type_id": "free_streets_scooter",
        "is_disabled": true,
        "current_range_meters": 1982,
        "lon": -3.6362119190181454,
        "bike_id": "free_streets_MADRID132",
        "lat": 40.373603794530105,
        "pricing_plan_id": "free_streets_plan_3"
      },
      {
        "is_reserved": true,
        "vehicle_type_id": "free_streets_motorbike",
        "is_disabled": true,
        "current_range_meters": 107997,
        "lon": -3.670826803847738,
        "bike_id": "free_streets_MADRID133",
        "lat": 40.40084089185234,
        "pricing_plan_id": "free_streets_plan_1"
      },
      {
        "is_reserved": true,
        "vehicle_type_id": "free_streets_scooter",
        "is_disabled": false,
        "current_range_meters": 12725,
        "lon": -3.788155952929698,
        "bike_id": "free_streets_MADRID134",
        "lat": 40.377952281847065,
        "pricing_plan_id": "free_streets_plan_1"
      },
      {
        "is_reserved": true,
        "vehicle_type_id": "free_streets_scooter",
        "is_disabled": false,
        "current_range_meters": 9244,
        "lon": -3.7115870062395477,
        "bike_id": "free_streets_MADRID135",
        "lat": 40.408954979529234,
        "pricing_plan_id": "free_streets_plan_1"
      },
      {
        "is_reserved": true,
        "vehicle_type_id": "free_streets_motorbike",
        "is_disabled": false,
        "current_range_meters": 74270,
        "lon": -3.789403411670188,
        "bike_id": "free_streets_MADRID136",
        "lat": 40.41063621713735,
        "pricing_plan_id": "free_streets_plan_1"
      },
      {
        "is_reserved": true,
        "vehicle_type_id": "free_streets_motorbike",
        "is_disabled": false,
        "current_range_meters": 62880,
        "lon": -3.671889973669429,
        "bike_id": "free_streets_MADRID137",
        "lat": 40.440178398457306,
        "pricing_plan_id": "free_streets_plan_3"
      },
      {
        "is_reserved": false,
        "vehicle_type_id": "free_streets_scooter",
        "is_disabled": true,
        "current_range_meters": 14153,
        "lon": -3.7466406428650045,
        "bike_id": "free_streets_MADRID138",
        "lat": 40.350123015140056,
        "pricing_plan_id": "free_streets_plan_2"
      },
      {
        "is_reserved": true,
        "vehicle_type_id": "free_streets_scooter",
        "is_disabled": true,
        "current_range_meters": 6857,
        "lon": -3.7341363704792414,
        "bike_id": "free_streets_MADRID139",
        "lat": 40.345987287962025,
        "pricing_plan_id": "free_streets_plan_2"
      },
      {
        "is_reserved": false,
        "vehicle_type_id": "free_streets_motorbike",
        "is_disabled": true,
        "current_range_meters": 80764,
        "lon": -3.72452324567906,
        "bike_id": "free_streets_MADRID140",
        "lat": 40.39038899443296,
        "pricing_plan_id": "free_streets_plan_1"
      },
      {
        "is_reserved": false,
        "vehicle_type_id": "free_streets_scooter",
        "is_disabled": true,
        "current_range_meters": 17484,
        "lon": -3.7223978432223372,
        "bike_id": "free_streets_MADRID141",
        "lat": 40.47609371902637,
        "pricing_plan_id": "free_streets_plan_3"
      },
      {
        "is_reserved": false,
        "vehicle_type_id": "free_streets_motorbike",
        "is_disabled": true,
        "current_range_meters": 109360,
        "lon": -3.781595626638719,
        "bike_id": "free_streets_MADRID142",
        "lat": 40.37380932741503,
        "pricing_plan_id": "free_streets_plan_3"
      },
      {
        "is_reserved": false,
        "vehicle_type_id": "free_streets_motorbike",
        "is_disabled": false,
        "current_range_meters": 88959,
        "lon": -3.714913628748172,
        "bike_id": "free_streets_MADRID143",
        "lat": 40.481827098688356,
        "pricing_plan_id": "free_streets_plan_2"
      },
      {
        "is_reserved": true,
        "vehicle_type_id": "free_streets_scooter",
        "is_disabled": true,
        "current_range_meters": 13293,
        "lon": -3.769587337613952,
        "bike_id": "free_streets_MADRID144",
        "lat": 40.43862850988763,
        "pricing_plan_id": "free_streets_plan_1"
      },
      {
        "is_reserved": false,
        "vehicle_type_id": "free_streets_motorbike",
        "is_disabled": true,
        "current_range_meters": 149346,
        "lon": -3.786941082667955,
        "bike_id": "free_streets_MADRID145",
        "lat": 40.3005324649544,
        "pricing_plan_id": "free_streets_plan_1"
      },
      {
        "is_reserved": false,
        "vehicle_type_id": "free_streets_scooter",
        "is_disabled": false,
        "current_range_meters": 12560,
        "lon": -3.770828364281145,
        "bike_id": "free_streets_MADRID146",
        "lat": 40.34330182355585,
        "pricing_plan_id": "free_streets_plan_3"
      },
      {
        "is_reserved": false,
        "vehicle_type_id": "free_streets_motorbike",
        "is_disabled": true,
        "current_range_meters": 185064,
        "lon": -3.680828040427339,
        "bike_id": "free_streets_MADRID147",
        "lat": 40.36058370968459,
        "pricing_plan_id": "free_streets_plan_2"
      },
      {
        "is_reserved": true,
        "vehicle_type_id": "free_streets_scooter",
        "is_disabled": false,
        "current_range_meters": 13932,
        "lon": -3.64680705925125,
        "bike_id": "free_streets_MADRID148",
        "lat": 40.358275151762776,
        "pricing_plan_id": "free_streets_plan_3"
      },
      {
        "is_reserved": true,
        "vehicle_type_id": "free_streets_motorbike",
        "is_disabled": true,
        "current_range_meters": 181572,
        "lon": -3.6043659449565504,
        "bike_id": "free_streets_MADRID149",
        "lat": 40.30887147684235,
        "pricing_plan_id": "free_streets_plan_3"
      },
      {
        "is_reserved": false,
        "vehicle_type_id": "free_streets_motorbike",
        "is_disabled": false,
        "current_range_meters": 128284,
        "lon": -3.6662422644029715,
        "bike_id": "free_streets_MADRID150",
        "lat": 40.39581228805278,
        "pricing_plan_id": "free_streets_plan_2"
      },
      {
        "is_reserved": true,
        "vehicle_type_id": "free_streets_motorbike",
        "is_disabled": true,
        "current_range_meters": 37522,
        "lon": -3.625918793551631,
        "bike_id": "free_streets_MADRID151",
        "lat": 40.392011338171564,
        "pricing_plan_id": "free_streets_plan_2"
      },
      {
        "is_reserved": true,
        "vehicle_type_id": "free_streets_motorbike",
        "is_disabled": false,
        "current_range_meters": 70342,
        "lon": -3.7273636103109737,
        "bike_id": "free_streets_MADRID152",
        "lat": 40.452084577253196,
        "pricing_plan_id": "free_streets_plan_2"
      },
      {
        "is_reserved": true,
        "vehicle_type_id": "free_streets_scooter",
        "is_disabled": true,
        "current_range_meters": 19133,
        "lon": -3.781380314846832,
        "bike_id": "free_streets_MADRID153",
        "lat": 40.365851842736475,
        "pricing_plan_id": "free_streets_plan_2"
      },
      {
        "is_reserved": true,
        "vehicle_type_id": "free_streets_scooter",
        "is_disabled": true,
        "current_range_meters": 2046,
        "lon": -3.7264278124121186,
        "bike_id": "free_streets_MADRID154",
        "lat": 40.30867195832238,
        "pricing_plan_id": "free_streets_plan_2"
      },
      {
        "is_reserved": true,
        "vehicle_type_id": "free_streets_scooter",
        "is_disabled": false,
        "current_range_meters": 16931,
        "lon": -3.7790397683889814,
        "bike_id": "free_streets_MADRID155",
        "lat": 40.45435736747119,
        "pricing_plan_id": "free_streets_plan_2"
      },
      {
        "is_reserved": false,
        "vehicle_type_id": "free_streets_motorbike",
        "is_disabled": false,
        "current_range_meters": 58574,
        "lon": -3.7029766981707932,
        "bike_id": "free_streets_MADRID156",
        "lat": 40.33089728525519,
        "pricing_plan_id": "free_streets_plan_2"
      },
      {
        "is_reserved": false,
        "vehicle_type_id": "free_streets_motorbike",
        "is_disabled": true,
        "current_range_meters": 70962,
        "lon": -3.6108924463735073,
        "bike_id": "free_streets_MADRID157",
        "lat": 40.412264806529976,
        "pricing_plan_id": "free_streets_plan_1"
      },
      {
        "is_reserved": true,
        "vehicle_type_id": "free_streets_motorbike",
        "is_disabled": true,
        "current_range_meters": 173056,
        "lon": -3.678085869745667,
        "bike_id": "free_streets_MADRID158",
        "lat": 40.33198098370281,
        "pricing_plan_id": "free_streets_plan_3"
      },
      {
        "is_reserved": false,
        "vehicle_type_id": "free_streets_motorbike",
        "is_disabled": false,
        "current_range_meters": 143265,
        "lon": -3.6036537661463517,
        "bike_id": "free_streets_MADRID159",
        "lat": 40.3615817024834,
        "pricing_plan_id": "free_streets_plan_2"
      },
      {
        "is_reserved": false,
        "vehicle_type_id": "free_streets_scooter",
        "is_disabled": true,
        "current_range_meters": 3952,
        "lon": -3.779645665982174,
        "bike_id": "free_streets_MADRID160",
        "lat": 40.44276398776013,
        "pricing_plan_id": "free_streets_plan_1"
      },
      {
        "is_reserved": false,
        "vehicle_type_id": "free_streets_motorbike",
        "is_disabled": false,
        "current_range_meters": 70720,
        "lon": -3.7698244693094183,
        "bike_id": "free_streets_MADRID161",
        "lat": 40.38587852208743,
        "pricing_plan_id": "free_streets_plan_2"
      },
      {
        "is_reserved": true,
        "vehicle_type_id": "free_streets_scooter",
        "is_disabled": true,
        "current_range_meters": 1221,
        "lon": -3.7300507292797422,
        "bike_id": "free_streets_MADRID162",
        "lat": 40.36604353174923,
        "pricing_plan_id": "free_streets_plan_3"
      },
      {
        "is_reserved": true,
        "vehicle_type_id": "free_streets_motorbike",
        "is_disabled": true,
        "current_range_meters": 177501,
        "lon": -3.618170760841792,
        "bike_id": "free_streets_MADRID163",
        "lat": 40.3713119120295,
        "pricing_plan_id": "free_streets_plan_3"
      },
      {
        "is_reserved": true,
        "vehicle_type_id": "free_streets_scooter",
        "is_disabled": true,
        "current_range_meters": 6306,
        "lon": -3.660509601360386,
        "bike_id": "free_streets_MADRID164",
        "lat": 40.321533346727456,
        "pricing_plan_id": "free_streets_plan_1"
      },
      {
        "is_reserved": false,
        "vehicle_type_id": "free_streets_motorbike",
        "is_disabled": false,
        "current_range_meters": 39387,
        "lon": -3.7884465269943406,
        "bike_id": "free_streets_MADRID165",
        "lat": 40.392368440722336,
        "pricing_plan_id": "free_streets_plan_1"
      },
      {
        "is_reserved": false,
        "vehicle_type_id": "free_streets_motorbike",
        "is_disabled": true,
        "current_range_meters": 187120,
        "lon": -3.778514374159958,
        "bike_id": "free_streets_MADRID166",
        "lat": 40.36792669149135,
        "pricing_plan_id": "free_streets_plan_2"
      },
      {
        "is_reserved": true,
        "vehicle_type_id": "free_streets_scooter",
        "is_disabled": false,
        "current_range_meters": 12531,
        "lon": -3.656581111417644,
        "bike_id": "free_streets_MADRID167",
        "lat": 40.48553412592028,
        "pricing_plan_id": "free_streets_plan_1"
      },
      {
        "is_reserved": true,
        "vehicle_type_id": "free_streets_motorbike",
        "is_disabled": true,
        "current_range_meters": 57526,
        "lon": -3.6420812167296113,
        "bike_id": "free_streets_MADRID168",
        "lat": 40.39436759804159,
        "pricing_plan_id": "free_streets_plan_3"
      },
      {
        "is_reserved": false,
        "vehicle_type_id": "free_streets_scooter",
        "is_disabled": true,
        "current_range_meters": 11233,
        "lon": -3.6308231221139997,
        "bike_id": "free_streets_MADRID169",
        "lat": 40.49246538293646,
        "pricing_plan_id": "free_streets_plan_1"
      },
      {
        "is_reserved": true,
        "vehicle_type_id": "free_streets_motorbike",
        "is_disabled": true,
        "current_range_meters": 62576,
        "lon": -3.6431543661801085,
        "bike_id": "free_streets_MADRID170",
        "lat": 40.40465181751321,
        "pricing_plan_id": "free_streets_plan_2"
      },
      {
        "is_reserved": true,
        "vehicle_type_id": "free_streets_motorbike",
        "is_disabled": false,
        "current_range_meters": 93544,
        "lon": -3.7325482032710187,
        "bike_id": "free_streets_MADRID171",
        "lat": 40.462194967927466,
        "pricing_plan_id": "free_streets_plan_2"
      },
      {
        "is_reserved": true,
        "vehicle_type_id": "free_streets_motorbike",
        "is_disabled": false,
        "current_range_meters": 29963,
        "lon": -3.7408055503353195,
        "bike_id": "free_streets_MADRID172",
        "lat": 40.45241986890199,
        "pricing_plan_id": "free_streets_plan_2"
      },
      {
        "is_reserved": false,
        "vehicle_type_id": "free_streets_scooter",
        "is_disabled": false,
        "current_range_meters": 14064,
        "lon": -3.649180273130794,
        "bike_id": "free_streets_MADRID173",
        "lat": 40.32192064730048,
        "pricing_plan_id": "free_streets_plan_2"
      },
      {
        "is_reserved": true,
        "vehicle_type_id": "free_streets_motorbike",
        "is_disabled": false,
        "current_range_meters": 134707,
        "lon": -3.7618216049318636,
        "bike_id": "free_streets_MADRID174",
        "lat": 40.384715182175945,
        "pricing_plan_id": "free_streets_plan_3"
      },
      {
        "is_reserved": false,
        "vehicle_type_id": "free_streets_scooter",
        "is_disabled": true,
        "current_range_meters": 4720,
        "lon": -3.683252863730238,
        "bike_id": "free_streets_MADRID175",
        "lat": 40.35967457814325,
        "pricing_plan_id": "free_streets_plan_2"
      },
      {
        "is_reserved": true,
        "vehicle_type_id": "free_streets_scooter",
        "is_disabled": false,
        "current_range_meters": 15043,
        "lon": -3.694002717070268,
        "bike_id": "free_streets_MADRID176",
        "lat": 40.43947846732443,
        "pricing_plan_id": "free_streets_plan_1"
      },
      {
        "is_reserved": false,
        "vehicle_type_id": "free_streets_scooter",
        "is_disabled": true,
        "current_range_meters": 10082,
        "lon": -3.611195040543241,
        "bike_id": "free_streets_MADRID177",
        "lat": 40.38608957582639,
        "pricing_plan_id": "free_streets_plan_3"
      },
      {
        "is_reserved": false,
        "vehicle_type_id": "free_streets_scooter",
        "is_disabled": true,
        "current_range_meters": 20351,
        "lon": -3.7812122200470255,
        "bike_id": "free_streets_MADRID178",
        "lat": 40.35831795807077,
        "pricing_plan_id": "free_streets_plan_3"
      },
      {
        "is_reserved": false,
        "vehicle_type_id": "free_streets_scooter",
        "is_disabled": true,
        "current_range_meters": 9690,
        "lon": -3.6566164330859774,
        "bike_id": "free_streets_MADRID179",
        "lat": 40.35268096419035,
        "pricing_plan_id": "free_streets_plan_2"
      },
      {
        "is_reserved": true,
        "vehicle_type_id": "free_streets_scooter",
        "is_disabled": true,
        "current_range_meters": 19344,
        "lon": -3.6491718539691926,
        "bike_id": "free_streets_MADRID180",
        "lat": 40.37729698691699,
        "pricing_plan_id": "free_streets_plan_1"
      },
      {
        "is_reserved": false,
        "vehicle_type_id": "free_streets_scooter",
        "is_disabled": true,
        "current_range_meters": 12914,
        "lon": -3.707557993842113,
        "bike_id": "free_streets_MADRID181",
        "lat": 40.478962082303994,
        "pricing_plan_id": "free_streets_plan_2"
      },
      {
        "is_reserved": false,
        "vehicle_type_id": "free_streets_motorbike",
        "is_disabled": true,
        "current_range_meters": 180096,
        "lon": -3.7318656748827514,
        "bike_id": "free_streets_MADRID182",
        "lat": 40.43396460527125,
        "pricing_plan_id": "free_streets_plan_1"
      },
      {
        "is_reserved": true,
        "vehicle_type_id": "free_streets_motorbike",
        "is_disabled": true,
        "current_range_meters": 35450,
        "lon": -3.7684373917651772,
        "bike_id": "free_streets_MADRID183",
        "lat": 40.34083156932027,
        "pricing_plan_id": "free_streets_plan_1"
      },
      {
        "is_reserved": true,
        "vehicle_type_id": "free_streets_motorbike",
        "is_disabled": false,
        "current_range_meters": 42503,
        "lon": -3.7361350034410252,
        "bike_id": "free_streets_MADRID184",
        "lat": 40.46674940323827,
        "pricing_plan_id": "free_streets_plan_2"
      },
      {
        "is_reserved": true,
        "vehicle_type_id": "free_streets_motorbike",
        "is_disabled": false,
        "current_range_meters": 22315,
        "lon": -3.658718352637395,
        "bike_id": "free_streets_MADRID185",
        "lat": 40.37845281952889,
        "pricing_plan_id": "free_streets_plan_3"
      },
      {
        "is_reserved": false,
        "vehicle_type_id": "free_streets_motorbike",
        "is_disabled": false,
        "current_range_meters": 142874,
        "lon": -3.6216097137414174,
        "bike_id": "free_streets_MADRID186",
        "lat": 40.40969086942432,
        "pricing_plan_id": "free_streets_plan_2"
      }
    ]
  },
  "ttl": 180,
  "version": "2.3"
}